#pragma once

#include <utility>

#include <lua/lopcodes.h>

std::pair<OpCode, OpMode> OpModeMap[] = {
    {OP_MOVE,       iABC},
    {OP_LOADI,      iAsBx},
    {OP_LOADF,      iAsBx},
    {OP_LOADK,      iABx},
    {OP_LOADKX,     iABC},
    {OP_LOADFALSE,  iABC},
    {OP_LFALSESKIP, iABC},
    {OP_LOADTRUE,   iABC},
    {OP_LOADNIL,    iABC},
    {OP_GETUPVAL,   iABC},
    {OP_SETUPVAL,   iABC},
    {OP_GETTABUP,   iABC},
    {OP_GETTABLE,   iABC},
    {OP_GETI,       iABC},
    {OP_GETFIELD,   iABC},
    {OP_SETTABUP,   iABC},
    {OP_SETTABLE,   iABC},
    {OP_SETI,       iABC},
    {OP_SETFIELD,   iABC},
    {OP_NEWTABLE,   iABC},
    {OP_SELF,       iABC},
    {OP_ADDI,       iABC},
    {OP_ADDK,       iABC},
    {OP_SUBK,       iABC},
    {OP_MULK,       iABC},
    {OP_MODK,       iABC},
    {OP_POWK,       iABC},
    {OP_DIVK,       iABC},
    {OP_IDIVK,      iABC},
    {OP_BANDK,      iABC},
    {OP_BORK,       iABC},
    {OP_BXORK,      iABC},
    {OP_SHRI,       iABC},
    {OP_SHLI,       iABC},
    {OP_ADD,        iABC},
    {OP_SUB,        iABC},
    {OP_MUL,        iABC},
    {OP_MOD,        iABC},
    {OP_POW,        iABC},
    {OP_DIV,        iABC},
    {OP_IDIV,       iABC},
    {OP_BAND,       iABC},
    {OP_BOR,        iABC},
    {OP_BXOR,       iABC},
    {OP_SHL,        iABC},
    {OP_SHR,        iABC},
    {OP_MMBIN,      iABC},
    {OP_MMBINI,     iABC},
    {OP_MMBINK,     iABC},
    {OP_UNM,        iABC},
    {OP_BNOT,       iABC},
    {OP_NOT,        iABC},
    {OP_LEN,        iABC},
    {OP_CONCAT,     iABC},
    {OP_CLOSE,      iABC},
    {OP_TBC,        iABC},
    {OP_JMP,        isJ},
    {OP_EQ,         iABC},
    {OP_LT,         iABC},
    {OP_LE,         iABC},
    {OP_EQK,        iABC},
    {OP_EQI,        iABC},
    {OP_LTI,        iABC},
    {OP_LEI,        iABC},
    {OP_GTI,        iABC},
    {OP_GEI,        iABC},
    {OP_TEST,       iABC},
    {OP_TESTSET,    iABC},
    {OP_CALL,       iABC},
    {OP_TAILCALL,   iABC},
    {OP_RETURN,     iABC},
    {OP_RETURN0,    iABC},
    {OP_RETURN1,    iABC},
    {OP_FORLOOP,    iABx},
    {OP_FORPREP,    iABx},
    {OP_TFORPREP,   iABx},
    {OP_TFORCALL,   iABC},
    {OP_TFORLOOP,   iABx},
    {OP_SETLIST,    iABC},
    {OP_CLOSURE,    iABx},
    {OP_VARARG,     iABC},
    {OP_VARARGPREP, iABC},
    {OP_EXTRAARG,   iAx}
};
